MANIFEST.in
setup.cfg
setup.py
superset/__init__.py
superset/cli.py
superset/config.py
superset/dataframe.py
superset/db_engine_specs.py
superset/extract_table_names.py
superset/forms.py
superset/jinja_context.py
superset/models.py
superset/results_backends.py
superset/security.py
superset/source_registry.py
superset/sql_lab.py
superset/sql_parse.py
superset/utils.py
superset/views.py
superset/viz.py
superset/bin/__init__.py
superset/bin/superset
superset/data/__init__.py
superset/data/birth_names.csv.gz
superset/data/birth_names.json.gz
superset/data/countries.json.gz
superset/data/countries.md
superset/data/countries.py
superset/data/energy.json.gz
superset/data/multiformat_time_series.json.gz
superset/data/random_time_series.json.gz
superset/data/san_francisco.csv.gz
superset/data/unicode_utf8_unixnl_test.csv
superset/data/__pycache__/__init__.cpython-35.pyc
superset/data/__pycache__/countries.cpython-35.pyc
superset/migrations/README
superset/migrations/__init__.py
superset/migrations/alembic.ini
superset/migrations/env.py
superset/migrations/script.py.mako
superset/migrations/versions/1226819ee0e3_fix_wrong_constraint_on_table_columns.py
superset/migrations/versions/12d55656cbca_is_featured.py
superset/migrations/versions/18e88e1cc004_making_audit_nullable.py
superset/migrations/versions/1a48a5411020_adding_slug_to_dash.py
superset/migrations/versions/1d2ddd543133_log_dt.py
superset/migrations/versions/1e2841a4128_.py
superset/migrations/versions/2591d77e9831_user_id.py
superset/migrations/versions/27ae655e4247_make_creator_owners.py
superset/migrations/versions/289ce07647b_add_encrypted_password_field.py
superset/migrations/versions/2929af7925ed_tz_offsets_in_data_sources.py
superset/migrations/versions/315b3f4da9b0_adding_log_model.py
superset/migrations/versions/33d996bcc382_update_slice_model.py
superset/migrations/versions/3b626e2a6783_sync_db_with_models.py
superset/migrations/versions/3c3ffe173e4f_add_sql_string_to_table.py
superset_hand.egg-info/PKG-INFO
superset_hand.egg-info/SOURCES.txt
superset_hand.egg-info/dependency_links.txt
superset_hand.egg-info/not-zip-safe
superset_hand.egg-info/requires.txt
superset_hand.egg-info/top_level.txt