Metadata-Version: 1.1
Name: superset-hand
Version: 0.14.1
Summary: A interactive data visualization platform build on SqlAlchemy and druid.io
Home-page: https://github.com/tddv/superset
Author: HAND
Author-email: 690416372@qq.com
License: UNKNOWN
Download-URL: https://github.com/tddv/superset/tarball/0.14.1
Platform: UNKNOWN
Classifier: Programming Language :: Python :: 2.7
Classifier: Programming Language :: Python :: 3.4
Classifier: Programming Language :: Python :: 3.5
